[
  {
    "ContainingType": "LivrariaApi.Controllers.AutorController",
    "Method": "BuscarAutorPorId",
    "RelativePath": "api/Autor/BuscarAutorPorId/{IdAutor}",
    "HttpMethod": "GET",
    "IsController": true,
    "Order": 0,
    "Parameters": [
      {
        "Name": "IdAutor",
        "Type": "System.Int32",
        "IsRequired": true
      }
    ],
    "ReturnTypes": [
      {
        "Type": "LivrariaApi.Models.ResponseModel\u00601[[LivrariaApi.Models.AutorModel, LivrariaApi, Version=1.0.0.0, Culture=neutral, PublicKeyToken=null]]",
        "MediaTypes": [
          "text/plain",
          "application/json",
          "text/json"
        ],
        "StatusCode": 200
      }
    ]
  },
  {
    "ContainingType": "LivrariaApi.Controllers.AutorController",
    "Method": "BuscarAutorPorIdLivro",
    "RelativePath": "api/Autor/BuscarAutorPorIdLivro/{IdLivro}",
    "HttpMethod": "GET",
    "IsController": true,
    "Order": 0,
    "Parameters": [
      {
        "Name": "IdLivro",
        "Type": "System.Int32",
        "IsRequired": true
      }
    ],
    "ReturnTypes": [
      {
        "Type": "LivrariaApi.Models.ResponseModel\u00601[[LivrariaApi.Models.AutorModel, LivrariaApi, Version=1.0.0.0, Culture=neutral, PublicKeyToken=null]]",
        "MediaTypes": [
          "text/plain",
          "application/json",
          "text/json"
        ],
        "StatusCode": 200
      }
    ]
  },
  {
    "ContainingType": "LivrariaApi.Controllers.AutorController",
    "Method": "CriarAutor",
    "RelativePath": "api/Autor/CriarAutor",
    "HttpMethod": "POST",
    "IsController": true,
    "Order": 0,
    "Parameters": [
      {
        "Name": "autorCriacaoDTO",
        "Type": "LivrariaApi.DTO.Autor.AutorCriacaoDTO",
        "IsRequired": true
      }
    ],
    "ReturnTypes": [
      {
        "Type": "LivrariaApi.Models.ResponseModel\u00601[[LivrariaApi.Models.AutorModel, LivrariaApi, Version=1.0.0.0, Culture=neutral, PublicKeyToken=null]]",
        "MediaTypes": [
          "text/plain",
          "application/json",
          "text/json"
        ],
        "StatusCode": 200
      }
    ]
  },
  {
    "ContainingType": "LivrariaApi.Controllers.AutorController",
    "Method": "EditarAutor",
    "RelativePath": "api/Autor/EditarAutor",
    "HttpMethod": "PUT",
    "IsController": true,
    "Order": 0,
    "Parameters": [
      {
        "Name": "autorEdicaoDTO",
        "Type": "LivrariaApi.DTO.Autor.AutorEdicaoDTO",
        "IsRequired": true
      }
    ],
    "ReturnTypes": [
      {
        "Type": "LivrariaApi.Models.ResponseModel\u00601[[LivrariaApi.Models.AutorModel, LivrariaApi, Version=1.0.0.0, Culture=neutral, PublicKeyToken=null]]",
        "MediaTypes": [
          "text/plain",
          "application/json",
          "text/json"
        ],
        "StatusCode": 200
      }
    ]
  },
  {
    "ContainingType": "LivrariaApi.Controllers.AutorController",
    "Method": "ExcluirAutor",
    "RelativePath": "api/Autor/ExcluirAutor",
    "HttpMethod": "DELETE",
    "IsController": true,
    "Order": 0,
    "Parameters": [
      {
        "Name": "IdAutor",
        "Type": "System.Int32",
        "IsRequired": false
      }
    ],
    "ReturnTypes": [
      {
        "Type": "LivrariaApi.Models.ResponseModel\u00601[[LivrariaApi.Models.AutorModel, LivrariaApi, Version=1.0.0.0, Culture=neutral, PublicKeyToken=null]]",
        "MediaTypes": [
          "text/plain",
          "application/json",
          "text/json"
        ],
        "StatusCode": 200
      }
    ]
  },
  {
    "ContainingType": "LivrariaApi.Controllers.AutorController",
    "Method": "ListarAutores",
    "RelativePath": "api/Autor/ListarAutores",
    "HttpMethod": "GET",
    "IsController": true,
    "Order": 0,
    "Parameters": [],
    "ReturnTypes": [
      {
        "Type": "LivrariaApi.Models.ResponseModel\u00601[[System.Collections.Generic.List\u00601[[LivrariaApi.Models.AutorModel, LivrariaApi, Version=1.0.0.0, Culture=neutral, PublicKeyToken=null]], System.Private.CoreLib, Version=8.0.0.0, Culture=neutral, PublicKeyToken=7cec85d7bea7798e]]",
        "MediaTypes": [
          "text/plain",
          "application/json",
          "text/json"
        ],
        "StatusCode": 200
      }
    ]
  }
]